LICENSE
MANIFEST.in
README.rst
requirements.txt
setup.cfg
setup.py
ckanext/__init__.py
ckanext/vtkjs/__init__.py
ckanext/vtkjs/plugin.py
ckanext/vtkjs/public/vtk-obj-zip.js
ckanext/vtkjs/public/vtk-stl.js
ckanext/vtkjs/public/vtk-vti.js
ckanext/vtkjs/public/vtk-vtp.js
ckanext/vtkjs/public/src/index_obj-zip.js
ckanext/vtkjs/public/src/index_stl.js
ckanext/vtkjs/public/src/index_vti.js
ckanext/vtkjs/public/src/index_vtp.js
ckanext/vtkjs/templates/not_authorized.html
ckanext/vtkjs/templates/view.html
ckanext/vtkjs/templates/vtkjs_form.html
ckanext/vtkjs/templates/vtkjs_view_obj-zip.html
ckanext/vtkjs/templates/vtkjs_view_stl.html
ckanext/vtkjs/templates/vtkjs_view_vti.html
ckanext/vtkjs/templates/vtkjs_view_vtp.html
ckanext/vtkjs/tests/__init__.py
ckanext/vtkjs/tests/test_plugin.py
ckanext_vtkjs.egg-info/PKG-INFO
ckanext_vtkjs.egg-info/SOURCES.txt
ckanext_vtkjs.egg-info/dependency_links.txt
ckanext_vtkjs.egg-info/entry_points.txt
ckanext_vtkjs.egg-info/namespace_packages.txt
ckanext_vtkjs.egg-info/top_level.txt