Metadata-Version: 1.1
Name: ckanext-vtkjs
Version: 0.0.1
Summary: STL and VTK viewer extension for CKAN
Home-page: https://github.com//ckanext-vtkjs
Author: UNKNOWN
Author-email: UNKNOWN
License: AGPL
Keywords: CKAN
Platform: UNKNOWN
Classifier: Development Status :: 4 - Beta
Classifier: License :: OSI Approved :: GNU Affero General Public License v3 or later (AGPLv3+)
Classifier: Programming Language :: Python :: 2.7
